pytbox/dida365.py
pytbox/victoriametrics.py
pytbox/common/__init__.py
pytbox/common/base.py
pytbox/utils/response.py
pytbox/utils/timeutils.py
pytbox-20250818.4.dist-info/METADATA
pytbox-20250818.4.dist-info/WHEEL
pytbox-20250818.4.dist-info/top_level.txt
pytbox-20250818.4.dist-info/RECORD
