Metadata-Version: 2.4
Name: pytbox
Version: 20250818.4
Summary: A collection of Python integrations and utilities (Feishu, Dida365, VictoriaMetrics, ...)
Author-email: mingming hou <houm01@foxmail.com>
License: MIT
Requires-Python: >=3.8
Requires-Dist: requests>=2.0
Requires-Dist: pydantic>=1.10
Provides-Extra: dev
Requires-Dist: pytest; extra == "dev"
Requires-Dist: black; extra == "dev"
Requires-Dist: ruff; extra == "dev"
Requires-Dist: python-dotenv; extra == "dev"
